{
  "status": 0,
  "result": [
    {
      "createdById": "005Dn000004XfgWIAS",
      "createdByName": "José Iago Barbosa Alves",
      "createdDate": "1970-01-01T00:00:00.000Z",
      "fileName": "appMenus/Salesforce1.appMenu",
      "fullName": "Salesforce1",
      "id": "",
      "lastModifiedById": "005Dn000004XfgWIAS",
      "lastModifiedByName": "José Iago Barbosa Alves",
      "lastModifiedDate": "1970-01-01T00:00:00.000Z",
      "namespacePrefix": "",
      "type": "AppMenu"
    },
    {
      "createdById": "005Dn000004XfgWIAS",
      "createdByName": "José Iago Barbosa Alves",
      "createdDate": "1970-01-01T00:00:00.000Z",
      "fileName": "appMenus/AppSwitcher.appMenu",
      "fullName": "AppSwitcher",
      "id": "",
      "lastModifiedById": "005Dn000004XfgWIAS",
      "lastModifiedByName": "José Iago Barbosa Alves",
      "lastModifiedDate": "1970-01-01T00:00:00.000Z",
      "namespacePrefix": "",
      "type": "AppMenu"
    }
  ]
}